nmraspecds/__init__.py
nmraspecds/analysis.py
nmraspecds/dataset.py
nmraspecds/io.py
nmraspecds/metadata.py
nmraspecds/plotting.py
nmraspecds/processing.py
nmraspecds/utils.py
nmraspecds-0.2.0.dist-info/LICENSE
nmraspecds-0.2.0.dist-info/METADATA
nmraspecds-0.2.0.dist-info/WHEEL
nmraspecds-0.2.0.dist-info/top_level.txt
nmraspecds-0.2.0.dist-info/RECORD
