Metadata-Version: 2.2
Name: nmraspecds
Version: 0.2.0
Summary: ASpecD derived Package for recipe driven data analysis of NMR spectra
Home-page: https://www.nmraspecds.de
Author: Mirjam Schröder, Florian Taube, Till Biskup
Author-email: code@mirjam-schroeder.de
License: BSD
Project-URL: Documentation, https://docs.nmraspecds.de
Project-URL: Source, https://github.com/MirjamSchr/nmraspecds
Keywords: spectroscopy,NMR,data processing and analysis,good scientific practice,recipe-driven data analysis,reproducible science
Classifier: Programming Language :: Python :: 3
Classifier: Programming Language :: Python :: 3.7
Classifier: Programming Language :: Python :: 3.8
Classifier: Programming Language :: Python :: 3.9
Classifier: Programming Language :: Python :: 3.10
Classifier: License :: OSI Approved :: BSD License
Classifier: Operating System :: OS Independent
Classifier: Intended Audience :: Science/Research
Classifier: Development Status :: 4 - Beta
Requires-Python: >=3.7
License-File: LICENSE
Requires-Dist: aspecd>=0.10
Requires-Dist: nmrglue
Requires-Dist: spindata
Provides-Extra: dev
Requires-Dist: prospector; extra == "dev"
Requires-Dist: black; extra == "dev"
Provides-Extra: docs
Requires-Dist: sphinx; extra == "docs"
Requires-Dist: sphinx-rtd-theme; extra == "docs"
Requires-Dist: sphinx_multiversion; extra == "docs"
Dynamic: author
Dynamic: author-email
Dynamic: classifier
Dynamic: description
Dynamic: description-content-type
Dynamic: home-page
Dynamic: keywords
Dynamic: license
Dynamic: project-url
Dynamic: provides-extra
Dynamic: requires-dist
Dynamic: requires-python
Dynamic: summary
